zucaro/__init__.py
zucaro/__main__.py
zucaro/account.py
zucaro/config.py
zucaro/downloader.py
zucaro/errors.py
zucaro/instance.py
zucaro/java_manager.py
zucaro/launcher.py
zucaro/library.py
zucaro/logging.py
zucaro/msapi.py
zucaro/osinfo.py
zucaro/rules.py
zucaro/utils.py
zucaro/version.py
zucaro/windows.py
zucaro/yggdrasil.py
zucaro/cli/__init__.py
zucaro/cli/account.py
zucaro/cli/config.py
zucaro/cli/instance.py
zucaro/cli/main.py
zucaro/cli/mod.py
zucaro/cli/play.py
zucaro/cli/utils.py
zucaro/cli/version.py
zucaro/java/SysDump.class
zucaro/java/__init__.py
zucaro/mod/__init__.py
zucaro/mod/curse.py
zucaro/mod/fabric.py
zucaro/mod/forge.py
zucaro/mod/ftb.py
zucaro/mod/modrinth.py
zucaro/mod/quilt.py
zucaro-0.5.2.dist-info/METADATA
zucaro-0.5.2.dist-info/WHEEL
zucaro-0.5.2.dist-info/entry_points.txt
zucaro-0.5.2.dist-info/licenses/LICENSE
zucaro-0.5.2.dist-info/RECORD
