Metadata-Version: 2.4
Name: zucaro
Version: 0.5.2
Summary: A very small CLI Minecraft launcher.
Author-email: Samuel Čavoj <samuel@cavoj.net>
License-File: LICENSE
Requires-Python: >=3.8
Requires-Dist: aiohttp==3.11.12
Requires-Dist: click~=8.1
Requires-Dist: colorama~=0.4
Requires-Dist: coloredlogs~=15.0
Requires-Dist: requests~=2.31
Requires-Dist: tqdm~=4.66
